bdns/api/__init__.py
bdns/api/__main__.py
bdns/api/commands/__init__.py
bdns/api/commands/actividades.py
bdns/api/commands/ayudasestado_busqueda.py
bdns/api/commands/beneficiarios.py
bdns/api/commands/concesiones_busqueda.py
bdns/api/commands/convocatorias.py
bdns/api/commands/convocatorias_busqueda.py
bdns/api/commands/convocatorias_documentos.py
bdns/api/commands/convocatorias_pdf.py
bdns/api/commands/convocatorias_ultimas.py
bdns/api/commands/finalidades.py
bdns/api/commands/grandesbeneficiarios_anios.py
bdns/api/commands/grandesbeneficiarios_busqueda.py
bdns/api/commands/instrumentos.py
bdns/api/commands/minimis_busqueda.py
bdns/api/commands/objetivos.py
bdns/api/commands/options.py
bdns/api/commands/organos.py
bdns/api/commands/organos_agrupacion.py
bdns/api/commands/organos_codigo.py
bdns/api/commands/organos_codigoadmin.py
bdns/api/commands/partidospoliticos_busqueda.py
bdns/api/commands/planesestrategicos.py
bdns/api/commands/planesestrategicos_busqueda.py
bdns/api/commands/planesestrategicos_documentos.py
bdns/api/commands/planesestrategicos_vigencia.py
bdns/api/commands/regiones.py
bdns/api/commands/reglamentos.py
bdns/api/commands/sanciones_busqueda.py
bdns/api/commands/sectores.py
bdns/api/commands/terceros.py
bdns/api/endpoints.py
bdns/api/fetch_write.py
bdns/api/types.py
bdns/api/utils.py
bdns_api-1.0.2.dist-info/LICENSE
bdns_api-1.0.2.dist-info/METADATA
bdns_api-1.0.2.dist-info/WHEEL
bdns_api-1.0.2.dist-info/entry_points.txt
bdns_api-1.0.2.dist-info/RECORD
