Metadata-Version: 2.3
Name: bdns-api
Version: 1.0.2
Summary: A comprehensive command-line tool for accessing Spanish government BDNS subsidies data
License: GPL-3.0
Keywords: bdns,subsidies,spanish-government,api,data,cli
Author: José María Cruz Lorite
Author-email: josemariacruzlorite@gmail.com
Requires-Python: >=3.11,<4.0
Classifier: Development Status :: 4 - Beta
Classifier: Environment :: Console
Classifier: Intended Audience :: Developers
Classifier: Intended Audience :: Science/Research
Classifier: License :: OSI Approved :: GNU General Public License v3 (GPLv3)
Classifier: Operating System :: OS Independent
Classifier: Programming Language :: Python :: 3
Classifier: Programming Language :: Python :: 3.11
Classifier: Programming Language :: Python :: 3.12
Classifier: Programming Language :: Python :: 3.13
Classifier: Topic :: Scientific/Engineering :: Information Analysis
Classifier: Topic :: Software Development :: Libraries :: Python Modules
Classifier: Topic :: Utilities
Requires-Dist: aiohttp (>=3.9.1,<4.0.0)
Requires-Dist: aiolimiter (>=1.0.0,<2.0.0)
Requires-Dist: duckdb (>=0.10.0,<0.11.0)
Requires-Dist: polars (>=0.20.0,<0.21.0)
Requires-Dist: pyarrow (>=15.0.0,<16.0.0)
Requires-Dist: requests (>=2.32.3,<3.0.0)
Requires-Dist: tenacity (>=8.2.3,<9.0.0)
Requires-Dist: tqdm (>=4.65.0,<5.0.0)
Requires-Dist: typer[all] (>=0.15.4,<0.16.0)
Project-URL: Documentation, https://github.com/cruzlorite/bdns-api#readme
Project-URL: Homepage, https://github.com/cruzlorite/bdns-api
Project-URL: Repository, https://github.com/cruzlorite/bdns-api
